diceware_list/__init__.py
diceware_list/diceware416.txt
diceware_list/dicewarekit.txt
diceware_list/libwordlist.py
diceware_list/wldownload.py
diceware_list/wlflakes.py
diceware_list-2.2.dist-info/LICENSE
diceware_list-2.2.dist-info/METADATA
diceware_list-2.2.dist-info/WHEEL
diceware_list-2.2.dist-info/entry_points.txt
diceware_list-2.2.dist-info/top_level.txt
diceware_list-2.2.dist-info/RECORD
