Metadata-Version: 2.1
Name: diceware_list
Version: 2.2
Summary: Tools for creating diceware wordlists
Author-email: Uli Fouquet <uli@gnufix.de>
License:                     GNU GENERAL PUBLIC LICENSE
Project-URL: Homepage, https://github.com/ulif/diceware-list
Project-URL: Bug Tracker, https://github.com/ulif/diceware-list/issues
Project-URL: Documentation, https://github.com/ulif/diceware-list
Keywords: diceware,wordlist,passphrase
Classifier: Operating System :: OS Independent
Classifier: Development Status :: 3 - Alpha
Classifier: Environment :: Console
Classifier: Intended Audience :: End Users/Desktop
Classifier: Intended Audience :: System Administrators
Classifier: Topic :: Utilities
Classifier: Topic :: Security :: Cryptography
Classifier: License :: OSI Approved :: GNU General Public License v3 or later (GPLv3+)
Classifier: Programming Language :: Python :: 3 :: Only
Classifier: Programming Language :: Python :: 3.7
Classifier: Programming Language :: Python :: 3.8
Classifier: Programming Language :: Python :: 3.9
Classifier: Programming Language :: Python :: 3.10
Classifier: Programming Language :: Python :: 3.11
Classifier: Programming Language :: Python :: 3.12
Classifier: Programming Language :: Python :: Implementation :: CPython
Requires-Python: >=3.7
License-File: LICENSE
Provides-Extra: tests
Requires-Dist: pytest>=2.8.3; extra == "tests"
Requires-Dist: pytest-cov; extra == "tests"
Requires-Dist: coverage; extra == "tests"
Provides-Extra: dev
Requires-Dist: black; extra == "dev"
Requires-Dist: ruff; extra == "dev"
Requires-Dist: tox; extra == "dev"
